Metadata-Version: 2.1
Name: fs-icloud
Version: 1.0.1
Summary: An icloud filesystem for pyfilesystem2 !
Home-page: https://github.com/dnmellen/icloudfs
Author: Diego Navarro Mellen
Author-email: dnmellen@gmail.com
License: MIT
Platform: UNKNOWN
License-File: LICENSE
